Metadata-Version: 1.1
Name: archetesting
Version: 0.0.3
Summary: This is the testing library
Home-page: UNKNOWN
Author: Arche
Author-email: rkdyava@gmail.com
License: UNKNOWN
Keywords: add
Platform: UNKNOWN
Classifier: Development Status :: 5 - Production/Stable
Classifier: Intended Audience :: Education
Classifier: Operating System :: Microsoft :: Windows :: Windows 10
Classifier: License :: OSI Approved :: MIT License
Classifier: Programming Language :: Python :: 3
